streamlit_secure_context/__init__.py
streamlit_secure_context-0.1.6.dist-info/licenses/LICENSE
streamlit_secure_context-0.1.6.dist-info/METADATA
streamlit_secure_context-0.1.6.dist-info/WHEEL
streamlit_secure_context-0.1.6.dist-info/top_level.txt
streamlit_secure_context-0.1.6.dist-info/RECORD
